docs/conf.py
examples/cloud/serverless_training/pytorch/data_ingestion.py
examples/cloud/serverless_training/pytorch/model_load_and_predict.py
examples/cloud/serverless_training/pytorch/model_training.py
tests/__init__.py
tests/conftest.py
tests/models/__init__.py
tests/models/test_cloud_utils.py
tests/models/test_pytorch_models.py
tests/models/test_sklearn_models.py
tests/models/test_tensorflow_keras_models.py
tests/readers/__init__.py
tests/readers/test_pytorch.py
tests/readers/test_pytorch_collators.py
tests/readers/test_ranges.py
tests/readers/test_tensor_schema.py
tests/readers/test_tensorflow.py
tests/readers/utils.py
tiledb/ml/__init__.py
tiledb/ml/version.py
tiledb/ml/models/__init__.py
tiledb/ml/models/_array_metadata.py
tiledb/ml/models/_base.py
tiledb/ml/models/_cloud_utils.py
tiledb/ml/models/_file_properties.py
tiledb/ml/models/pytorch.py
tiledb/ml/models/sklearn.py
tiledb/ml/models/tensorflow_keras.py
tiledb/ml/readers/__init__.py
tiledb/ml/readers/_pytorch_collators.py
tiledb/ml/readers/pytorch.py
tiledb/ml/readers/tensorflow.py
tiledb/ml/readers/types.py
tiledb/ml/readers/_tensor_schema/__init__.py
tiledb/ml/readers/_tensor_schema/base.py
tiledb/ml/readers/_tensor_schema/base_sparse.py
tiledb/ml/readers/_tensor_schema/dense.py
tiledb/ml/readers/_tensor_schema/mapped.py
tiledb/ml/readers/_tensor_schema/query.py
tiledb/ml/readers/_tensor_schema/ragged.py
tiledb/ml/readers/_tensor_schema/ranges.py
tiledb/ml/readers/_tensor_schema/sparse.py
tiledb/ml/readers/_tensor_schema/sparse_to_dense.py
tiledb_ml-0.10.1.dist-info/licenses/LICENSE
tiledb_ml-0.10.1.dist-info/METADATA
tiledb_ml-0.10.1.dist-info/WHEEL
tiledb_ml-0.10.1.dist-info/top_level.txt
tiledb_ml-0.10.1.dist-info/RECORD
