Metadata-Version: 2.4
Name: tiledb-ml
Version: 0.10.1
Summary: Package supports all machine learning functionality for TileDB Embedded and TileDB Cloud
Home-page: https://github.com/TileDB-Inc/TileDB-ML
Author: TileDB, Inc.
Author-email: help@tiledb.io
License: MIT
Project-URL: Bug Tracker, https://github.com/TileDB-Inc/TileDB-ML/issues
Project-URL: Documentation, https://docs.tiledb.com
Keywords: tiledb,ml
Platform: any
Classifier: Development Status :: 4 - Beta
Classifier: Intended Audience :: Developers
Classifier: Intended Audience :: Information Technology
Classifier: Intended Audience :: Science/Research
Classifier: Programming Language :: Python
Classifier: Topic :: Software Development :: Libraries :: Python Modules
Classifier: Topic :: Scientific/Engineering :: Artificial Intelligence
Classifier: Operating System :: Unix
Classifier: Operating System :: POSIX :: Linux
Classifier: Operating System :: MacOS :: MacOS X
Classifier: Programming Language :: Python :: 3
Classifier: Programming Language :: Python :: 3.7
Classifier: Programming Language :: Python :: 3.8
Classifier: License :: OSI Approved :: MIT License
Requires-Python: >=3.7
License-File: LICENSE
Requires-Dist: sparse
Requires-Dist: tiledb>=0.14
Requires-Dist: wrapt
Provides-Extra: tensorflow
Requires-Dist: tensorflow>=2.6; extra == "tensorflow"
Provides-Extra: pytorch
Requires-Dist: torch>=1.11; extra == "pytorch"
Requires-Dist: torchdata<=0.11.0,>=0.6.0; extra == "pytorch"
Provides-Extra: sklearn
Requires-Dist: scikit-learn>=1.3.0; extra == "sklearn"
Provides-Extra: cloud
Requires-Dist: tiledb-client; extra == "cloud"
Provides-Extra: full
Requires-Dist: scikit-learn>=1.3.0; extra == "full"
Requires-Dist: tensorflow>=2.6; extra == "full"
Requires-Dist: tiledb-client; extra == "full"
Requires-Dist: torch>=1.11; extra == "full"
Requires-Dist: torchdata<=0.11.0,>=0.6.0; extra == "full"
Requires-Dist: torchvision; extra == "full"
Dynamic: license-file
Dynamic: provides-extra
Dynamic: requires-dist
